tmeasure/__init__.py
tmeasure-2.1.dist-info/LICENSE
tmeasure-2.1.dist-info/METADATA
tmeasure-2.1.dist-info/WHEEL
tmeasure-2.1.dist-info/top_level.txt
tmeasure-2.1.dist-info/RECORD
